pycup/GLUE.py
pycup/GWO.py
pycup/MFO.py
pycup/MODE.py
pycup/MOMFO.py
pycup/MOPSO.py
pycup/NSGA2.py
pycup/PESTclasses.py
pycup/PSO.py
pycup/Reslib.py
pycup/SCA.py
pycup/SOA.py
pycup/SSA.py
pycup/TOPSIS.py
pycup/TSA.py
pycup/WOA.py
pycup/__init__.py
pycup/calc_utils.py
pycup/evaluation_metrics.py
pycup/integrate.py
pycup/multi_jobs.py
pycup/plot.py
pycup/progress_bar.py
pycup/sampling.py
pycup/save.py
pycup/template.py
pycup/test.py
pycup/test_functions.py
pycup/uncertainty_analysis_fun.py
pycup/utilize.py
pycup/document/Documentation.pdf
pycup-0.1.7.2.dist-info/LICENSE
pycup-0.1.7.2.dist-info/METADATA
pycup-0.1.7.2.dist-info/WHEEL
pycup-0.1.7.2.dist-info/top_level.txt
pycup-0.1.7.2.dist-info/RECORD
