Metadata-Version: 2.1
Name: pycup
Version: 0.1.7.2
Summary: An auto-calibration tool for environmental models based on heuristic algorithms and uncertainty estimation theory.
Home-page: https://github.com/QianyangWang/PyCUP
Author: Qianyang Wang
Author-email: wqy07010944@hotmail.com
License: MIT License
Project-URL: Documentation, https://github.com/QianyangWang/PyCUP/DOCUMENT
Project-URL: Source, https://github.com/QianyangWang/PyCUP/pycup
Keywords: optimization
Platform: UNKNOWN
Requires-Python: >=3
Requires-Dist: numpy
Requires-Dist: matplotlib
Requires-Dist: scipy
Requires-Dist: pyDOE
Requires-Dist: statsmodels
Requires-Dist: pandas
Requires-Dist: prettytable
